{
    "maps": [

    {
        "id": 2,
        "mapURL": "mapADG",
        "bounds": [
            [45.213278, 37.772987],
            [43.949287, 41.32026]
            ],
        "title": "Адыгея",
        "center": [44.581469077472825, 39.585937466472394],
        "zoom": 9
    },
    {
        "id": 3,
        "mapURL": "mapALT",
        "bounds": [
            [54.572437, 75.830861],
            [50.485886, 89.234181]
         ],
        "title": "Алтайский край",
        "center": [52.809795, 82.664357], 
        "zoom": 7
    },
    {
        "id": 4,
        "mapURL": "mapALY",
        "bounds": [
            [52.745506, 81.048664],
            [49.062244, 92.749103]
            ],
        "title": "Алтай",
        "center": [50.981847, 86.970294],
        "zoom":7
    },
    {
        "id": 5,
        "mapURL": "mapAMU",
        "bounds": [
            [57.39999174094969, 117.0878903567791],
            [48.54861464190667, 137.43457004427913]
            ],
        "title":"Амурская обл.",
        
        "center": [52.98430329, 127.2612302],

        "zoom":6.1
    },
    {
        "id": 6,
        "mapURL": "mapARK",
        "bounds": [
            [66.917588, 28.275334],
            [60.457798, 57.703223]
        ],
        "title": "Архангельская обл.",
        "center": [64.157677, 43.390694],
        "zoom": 7
    },
    {
        "id": 7,
        "mapURL": "mapAST",
        "bounds": [
            [48.928381, 41.984886],
            [45.353710, 52.481423]
        ],
        "title": "Астраханская обл.",
        "center": [47.239847, 47.112810],
        "zoom": 7.2
    },
    {
        "id": 8,
        "mapURL": "mapBAS",
        "bounds": [
            [56.594987, 47.864317],
            [51.368391, 65.684862]
        ],
        "title": "Башкирия",
        "center": [54.516108, 56.803029],
        "zoom": 7
    },
    {
        "id": 9,
        "mapURL": "mapBEL",
        "bounds": [
            [51.468899, 34.657108],
            [49.784058, 39.880325]
        ],
        "title": "Белгородская обл",
        "center": [50.780235, 37.333262],
        "zoom": 8.5
    },
    {
        "id": 10,
        "mapURL": "mapBRY",
        "bounds": [
            [54.136493, 29.358286],
            [51.785872, 37.172141]
        ],
        "title": "Брянская обл.",
        "center": [52.950261, 33.349817],
        "zoom": 8
    },
    {
        "id": 11,
        "mapURL": "mapBUR",
        "bounds": [
            [57.472112, 95.022667],
            [49.835450, 120.737773]
        ],
        "title": "Бурятия",
        "center": [54.382598, 108.481210],
        "zoom": 7
    },
    {
        "id": 12,
        "mapURL": "mapCEC",
        "bounds": [
            [44.040334, 43.550393],
            [42.443981, 47.937707]
        ],
        "title": "Чечня",
        "center": [43.376765, 45.783333],
        "zoom": 9
    },
    {
        "id": 13,
        "mapURL": "mapCHE",
        "bounds": [
            [55.500794, 52.440320],
            [51.946390, 67.931042]
        ],
        "title": "Челябинская обл.",
        "center": [53.74741146761635,60.14794908463956],
        "zoom": 7
    },
    {
        "id": 14,
        "mapURL": "mapCHU",
        "bounds": [
            [72.851613, 155.770449],
            [59.726193, 166.320707

        ]
        ],
        "title": "Чукотка",
        "center": [66.8606169763111, 160.74695226867217],
        "zoom": 6.8
    },
    {
        "id": 15,
        "mapURL": "mapCUV",
        "bounds": [
            [56.321345, 44.031768],
            [54.664031, 50.173124]
        ],
        "title": "Чувашия",
        "center": [55.535432, 47.117058],
        "zoom": 8
    },
    {
        "id": 16,
        "mapURL": "mapDAG",
        "bounds": [
            [45.144587, 41.354015],
            [41.120948, 52.314801]
        ],
        "title": "Дагестан",
        "center": [43.03677585761058, 47.50488281250001],
        "zoom": 7
    },
    {
        "id": 17,
        "mapURL": "mapDNR",
        "bounds": [
            [49.249923, 34.263092],
            [46.921721, 41.308153]
        ],
        "title": "ДНР",
        "center": [ 48.28337892121624, 37.93001830200241 ],
        "zoom": 8
    },
    {
        "id": 18,
        "mapURL": "mapKHA",
        "bounds": [
            [63.088791998503744, 120.93310520052913],
            [46.47418609951052, 156.52441352605823]
        ],
        "title": "Хабаровский край",
        "center": [55.42104634513772, 138.6087350631413],
        "zoom": 5.1
    },
    {
        "id": 19,
        "mapURL": "mapHER",
        "bounds": [
            [47.585791, 30.925791],
            [45.932871, 35.742820]
        ],
        "title": "Херсонская обл.",
        "center": [46.846696, 33.498212],
        "zoom": 9
    },
    {
        "id": 20,
        "mapURL": "mapING",
        "bounds": [
            [43.648981, 43.402680],
            [42.580375, 46.314057]
        ],
        "title": "Ингушетия",
        "center": [ 43.08774568719714, 44.930786099284894],
        "zoom": 9
    },
    {
        "id": 21,
        "mapURL": "mapIRK",
        "bounds": [
            [64.605896, 80.897646],
            [50.705961, 133.894685]
        ],
        "title": "Иркутская обл.",
        "center": [
            57.38815163445744, 106.42675727605823],
        "zoom": 5
    },
    {
        "id": 22,
        "mapURL": "mapIVA",
        "bounds": [
            [57.832824, 38.410642],
            [56.202648, 44.218348]
        ],
        "title": "Ивановская обл.",
        "center": [57.072611, 41.400355],
        "zoom": 8
    },
    {
        "id": 23,
        "mapURL": "mapKAM",
        "bounds": [
            [66.93006025862448, 144.94921982288363],
            [48.3416461723746, 186.25781357288363]
        ],
        "title": "Камчатская обл.",
        "center": [59.102458, 164.442199],
        "zoom":5
    },
    {
        "id": 24,
        "mapURL": "mapKBB",
        "bounds": [
            [44.056101, 41.769019],
            [42.890308, 44.386085]
        ],
        "title": "Кабардино-Балкария",
        "center": [ 43.49517380652889,  43.02685540169478],
        "zoom": 9
    },
    {
        "id": 25,
        "mapURL": "mapKCC",
        "bounds": [
            [44.489411, 39.902226],
            [43.215810, 43.421443]
        ],
        "title": "Карачаево-Черкессия",
        "center": [ 43.8472052919158,  41.75683580338955],
        "zoom": 9
    },
    {
        "id": 26,
        "mapURL": "mapKDA",
        "bounds": [
            [46.902830, 34.288819],
            [43.430352, 44.503365]
        ],
        "title": "Краснодарский край",
        "center": [45.05489709481256, 38.90039049088955],
        "zoom": 8
    },
    {
        "id": 27,
        "mapURL": "mapKEM",
        "bounds": [
            [56.890728, 78.858511],
            [52.232084, 94.919277]
        ],
        "title": "Кемеровская обл.",
        "center": [54.876310, 87.220978],
        "zoom": 7
    },
    {
        "id": 28,
        "mapURL": "mapKGD",
        "bounds": [
            [55.390884, 19.249118],
            [54.234097, 23.249215]
        ],
        "title": "Калининградская обл.",
        "center": [54.812282, 21.422755],
        "zoom": 9
    },
    {
        "id": 29,
        "mapURL": "mapKGN",
        "bounds": [
            [56.782713, 60.493403],
            [54.172646, 70.172991]
        ],
        "title": "Курганская обл.",
        "center": [55.628030, 65.328644],
        "zoom": 8
    },
    {
        "id": 30,
        "mapURL": "mapKIR",
        "bounds": [
            [61.457346, 39.068627],
            [55.734185, 61.197594]
        ],
        "title": "Кировская обл.",
        "center": [58.740050, 50.910839],
        "zoom": 7
    },
    {
        "id": 31,
        "mapURL": "mapKKS",
        "bounds": [
            [55.536586, 82.666469],
            [51.174381, 97.168422]
        ],
        "title":"Хакасия",
        "center": [ 53.477585426752476, 89.72753852605821],
        "zoom": 8
    },
    {
        "id": 32,
        "mapURL": "mapKLM",
        "bounds":[
            [48.480455, 38.657609],
            [44.457580, 50.292131]
        ],
        "title":"Калмыкия",
        "center": [46.732590, 43.964006],
        "zoom": 7
    },
    {
        "id": 33,
        "mapURL":"mapKOM",
        "bounds": [
            [68.830098, 32.546500],
            [58.697325, 79.260368]
        ],
        "title":"Коми",
        "center": [64.14128619869473, 53.868163526058204],
        "zoom": 5
    },
    {
        "id": 34,
        "mapURL":"mapKOS",
        "bounds":[
            [59.714489, 39.149232],
            [57.215387, 48.837926]
        ],
        "title": "Костромская обл.",
        "center": [ 58.45692981467992, 43.73437486588955],
        "zoom": 7
    },
    {
        "id": 35,
        "mapURL":"mapKRL",
        "bounds": [
            [66.801771, 19.519483],
            [60.579183, 47.673220]
        ],
        "title":"Карелия",
        "center": [64.094662, 34.073533],
        "zoom": 7
    },
    {
        "id": 36,
        "mapURL": "mapKRM",
        "bounds": [
            [46.320943, 31.660492],
            [44.277257, 37.483246]
        ],
        "title": "Крым",
        "center": [45.391310, 34.549896],
        "zoom": 8
    },
    {
        "id": 37,
        "mapURL":"mapKYA",
        "bounds": [
            [78.971806, 18.322018],
            [52.415449, 159.951850]
        ],
        "title":"Красноярский край",
        "center": [69.374346, 99.090002],
        "zoom": 3.8
    },
    {
        "id": 38,
        "mapURL":"mapLEN",
        "bounds": [
            [61.349469, 26.276204],
            [58.601293, 37.257729]
        ],
        "title": "Ленинградская обл.",
        "center": [60.071237, 32.166200],
        "zoom": 7
    },
    {
        "id": 39,
        "mapURL":"mapLIP",
        "bounds":[
            [53.634191, 36.326470],
            [51.865611, 42.138237]
        ],
        "title":"Липецкая обл.",
        "center": [52.788785, 39.353203],
        "zoom": 8
    },
    {
        "id": 40,
        "mapURL":"mapLNR",
        "bounds": [
            [50.134614, 35.506274],
            [47.820994, 42.551336]
        ],
        "title":"Луганская обл.",
        "center": [49.004276, 39.257455],
        "zoom": 8
    },
    {
        "id": 41,
        "mapURL":"mapMAG",
        "bounds": [
            [57.62220852219465, 166.04986716201574],
            [67.12695706276003, 142.52622995079716]
        ],
        "title":"Магаданская",
        "center":[63.193708, 154.710329],
        "zoom": 5.8
    },
    {
        "id": 42,
        "mapURL":"mapMEL",
        "bounds": [
            [57.373525, 45.066874],
            [55.809758, 50.760955]
        ],
        "title":"Марий Эл",
        "center": [56.638745, 48.126636],
        "zoom": 8
    },
    {
        "id": 43,
        "mapURL":"mapMOR",
        "bounds": [
            [55.287274, 41.428798],
            [53.592994, 47.456914]
        ],
        "title":"Мордовия",
        "center":[54.456837, 44.579445],
        "zoom": 8
    },
    {
        "id": 44,
        "mapURL":"mapMOS",
        "bounds": [
            [57.024888, 32.670969],
            [54.191437, 42.610833]
        ],
        "title":"Московская обл.",
        "center":[55.725256, 37.916380],
        "zoom": 7.5
    },
    {
        "id": 45,
        "mapURL": "mapMSK",
        "bounds": [
            [56.005486, 35.879540],
            [55.157564, 38.898151]
        ],
        "title":"Москва",
        "center":[55.596036, 37.525435],
        "zoom": 9
    },
    {
        "id": 46,
        "mapURL": "mapMUR",
        "bounds": [
            [69.928259, 24.639040],
            [66.167870, 44.518767]
        ],
        "title":"Мурманская обл.",
        "center": [68.304036, 34.661924],
        "zoom": 7
    },
    {
        "id": 47,
        "mapURL": "mapNEN",
        "bounds": [
            [70.831128, 39.762222],
            [65.404561, 68.854017]
        ],
        "title":"Ненецкий край",
        "center": [68.383984, 55.011244],
        "zoom":7
    },
    {
        "id": 48,
        "mapURL": "mapNGR",
        "bounds": [
            [59.586085, 27.661496],
            [56.795120, 38.190052]
        ],
        "title":"Новгородская обл.",
        "center": [58.439927, 32.937095],
        "zoom": 7.5
    },
    {
        "id": 49,
        "mapURL":"mapNIZ",
        "bounds": [
            [58.090884, 38.369067],
            [54.538522, 51.235725]
        ],
        "title":"Нижегородская обл.",
        "center": [56.325764, 44.879796],
        "zoom": 7
    },
    {
        "id": 50,
        "mapURL":"mapNVS",
        "bounds": [
            [57.398615, 72.454789],
            [53.035713, 88.000442]
        ],
        "title":"Новосибирская обл.",
        "center": [55.398876, 80.496780],
        "zoom": 6.5
    },
    {
        "id": 51,
        "mapURL": "mapOMS",
        "bounds": [
            [59.028746, 62.476390],
            [53.066160, 83.805207]
        ],
        "title":"Омская обл.",
        "center": [
            55.833377883804474, 73.45019504427911],
        "zoom": 6.5
    }, 
    {
        "id": 52,
        "mapURL":"mapORE",
        "bounds": [
            [54.656054, 48.756568],
            [50.296254, 63.211946]
        ],
        "title": "Оренбургская обл.",
        "center":[52.627887, 56.004997],
        "zoom": 6.5
    },
    {
        "id": 53, 
        "mapURL": "mapORL",
        "bounds": [
            [53.776066, 33.164195],
            [51.836088, 39.588417]
        ],
        "title":"Орловская обл.",
        "center": [52.851281, 36.455983],
        "zoom": 7.5
    },
    {
        "id": 54,
        "mapURL":"mapPER",
        "bounds": [
            [61.611299, 44.965738],
            [56.139729, 66.339840]
        ],
        "title":"Пермская обл.",
        "center":[59.127548, 56.347146],
        "zoom": 6.5
    },
    {
        "id": 55,
        "mapURL":"mapPNZ",
        "bounds": [
            [54.164250, 41.261667],
            [52.233672, 47.690443]
        ],
        "title":"Пензенская обл.",
        "center": [53.207106, 44.680938],
        "zoom": 7.5
    },
    {
        "id": 56,
        "mapURL":"mapPRI",
        "bounds":[
            [49.160067, 128.416995],
            [41.318975, 141.292972]
        ],
        "title":"Приморский край",
        "center":[45.682651, 135.105669],
        "zoom":6.7
    },
    {
        "id": 57,
        "mapURL":"mapPSK",
        "bounds": [
            [59.070408, 22.982801],
            [55.603941, 35.840352]
        ],
        "title":"Псковская обл.",
        "center":[57.383015, 29.347835],
        "zoom":7
    },
    {
        "id":58,
        "mapURL":"mapROS",
        "bounds": [
            [50.266774, 34.821934],
            [45.948667, 47.533677]
        ],
        "title":"Ростовская обл.",
        "center": [47.992962, 41.345101],
        "zoom": 7
    },
    {
        "id": 59,
        "mapURL":"mapRYA",
        "bounds": [
            [55.469274, 36.817727],
            [53.251817, 44.464211]
        ],
        "title":"Рязанская обл.",
        "center": [54.441052, 40.673928],
        "zoom": 7
    },
    {
        "id": 60,
        "mapURL":"mapSAK",
        "bounds": [
            [77.630926, 97.985748],
            [54.035023, 170.116814]
        ],
        "title":"Якутия",
        "center":[67.958333, 133.927561],
        "zoom":4
    },
    {
        "id": 61,
        "mapURL":"mapSAM",
        "bounds": [
            [54.817829, 44.938983],
            [51.634311, 55.610939]
        ],
        "title":"Самарская обл.",
        "center":[53.298546, 50.418361],
        "zoom":7
    },
    {
        "id": 62,
        "mapURL":"mapSAR",
        "bounds": [
            [52.990449, 41.260592],
            [49.672518, 51.940095]
        ],
        "title":"Саратовская обл.",
        "center":[51.446264, 46.732422],
        "zoom":7
    },
    {
        "id": 63,
        "mapURL":"mapSEA",
        "bounds": [
            [43.938032, 42.214636],
            [42.509116, 46.131441]
        ],
        "title":"Северная Осетия",
        "center":[ 43.02312320135036, 44.240844659507275],
        "zoom":8.5
    },
    {
        "id": 64,
        "mapURL":"mapSKL",
        "bounds": [
            [41.04953101186749, 162.34716810286048],
            [55.66767175316764, 136.48535169661048]
        ],
        "title":"Сахалинская обл.",
        "center":[50.77815527465925, 145.86767591536048],
        "zoom":6
    },
    {
        "id": 65,
        "mapURL":"mapSMO",
        "bounds": [
            [56.045587, 28.660987],
            [53.469352, 37.512593]
        ],
        "title":"Смоленская обл.",
        "center":[54.92461660960982,32.890869006514556],
        "zoom":7.5
    },
    {
        "id": 66,
        "mapURL":"mapSPB",
        "bounds": [
            [60.270304, 28.773823],
            [59.603001, 31.441812]
        ],
        "title":"Санкт-Петербург",
        "center":[59.937386, 30.162536],
        "zoom":9
    },
    {
        "id": 67,
        "mapURL":"mapSTA",
        "bounds": [
            [46.309794, 39.385378],
            [43.597143, 47.158204]
        ],
        "title":"Ставропольский край",
        "center":[45.031650, 43.428346],
        "zoom":7.5
    },
    {
        "id": 68,
        "mapURL":"mapSVE",
        "bounds": [
            [62.328727, 48.707557],
            [55.747152, 74.440872]
        ],
        "title":"Свердловская обл.",
        "center":[59.265912, 61.856498],
        "zoom":7
    },
    {
        "id": 69,
        "mapURL":"mapSVT",
        "bounds": [
            [44.853508, 32.985047],
            [44.376702, 34.318098]
        ],
        "title":"Севастополь",
        "center":[44.619623, 33.710537],
        "zoom":10
    },
    {
        "id": 70,
        "mapURL":"mapTYV",
        "bounds": [
            [53.767947, 87.636141],
            [49.788154, 100.530116]
        ],
        "title":"Тыва",
        "center":[51.852916, 94.511106],
        "zoom":7
    },
    {
        "id": 71,
        "mapURL":"mapUDM",
        "bounds": [
            [58.633398, 47.498212],
            [55.739494, 58.072052]
        ],
        "title":"Удмуртия",
        "center":[57.263810, 52.917211],
        "zoom":7
    },
    {
        "id": 72,
        "mapURL":"mapULY",
        "bounds": [
            [54.895333, 44.174083],
            [52.599466, 51.946909]
        ],
        "title":"Ульяновская обл.",
        "center":[53.871726, 48.184092],
        "zoom":7.5
    },
    {
        "id": 73,
        "mapURL":"mapVGG",
        "bounds": [
            [61.994984, 33.182155],
            [58.094441, 48.650904]
        ],
        "title":"Вологодская обл.",
        "center":[60.173498, 41.004420],
        "zoom":7
    },
    {
        "id": 74,
        "mapURL":"mapVLA",
        "bounds": [
            [56.853092, 37.388618],
            [55.059079, 43.835606]
        ],
        "title":"Владимирская обл.",
        "center":[56.007230, 40.721383],
        "zoom":7.8
    },
    {
        "id": 75,
        "mapURL":"mapVLG",
        "bounds": [
            [51.326282, 38.238033],
            [47.402543, 50.304299]
        ],
        "title":"Волгоградская обл.",
        "center":[ 49.45812747258603, 46.05249010026455],
        "zoom":7
    },
    {
        "id": 76,
        "mapURL":"mapVOR",
        "bounds": [
            [52.101447, 36.692405],
            [49.640959, 44.382834]
        ],
        "title":"Воронежская обл.",
        "center":[50.915159, 40.510154],
        "zoom":7.5
    },
    {
        "id": 77,
        "mapURL":"mapYAN",
        "bounds": [
            [73.668777, 42.975763],
            [62.335596, 105.114430]
        ],
        "title":"Ямало-Ненецкий округ",
        "center":[69.323178, 72.682792],
        "zoom":6
    },
    {
        "id": 78,
        "mapURL":"mapYAR",
        "bounds": [
            [58.957501, 34.788974],
            [56.572832, 43.634325]
        ],
        "title":"Ярославская обл.",
        "center":[57.796520, 39.211650],
        "zoom":8
    },
    {
        "id": 79,
        "mapURL":"mapYEV",
        "bounds": [
            [49.95201733809378, 130.2981625283045],
            [47.1854965856898, 135.19795248141892]
        ],
        "title":"Еврейская авт. обл.",
        "center":[48.638824, 132.943880],
        "zoom":7.8
    },
    {
        "id": 80,
        "mapURL":"mapZAB",
        "bounds": [
            [58.404413, 99.667151],
            [49.328482, 130.714512]
        ],
        "title":"Забайкальский край",
        "center":[54.370762, 115.487462],
        "zoom":7
    },
    {
        "id": 81,
        "mapURL":"mapZAP",
        "bounds": [
            [48.109112, 33.123542],
            [46.314970, 38.467068]
        ],
        "title":"Запорожская обл.",
        "center":[47.296465, 35.859458],
        "zoom":8.5
    },
    {
        "id": 82,
        "mapURL":"mapKHM",
        "bounds": [
            [65.905372, 56.553159],
            [58.484727, 88.553932]
        ],
        "title":"Ханты-Мансийский авт. округ",
        "center":[62.382171, 72.493166],
        "zoom":5.5
    },
    {
        "id": 83,
        "mapURL":"mapKLU",
        "bounds": [
            [55.480317, 31.280179],
            [53.147676, 39.272825]
        ],
        "title":"Калужская обл.",
        "center":[54.383308, 35.446317],
        "zoom":7.5
    },
    {
        "id": 84,
        "mapURL":"mapKRS",
        "bounds": [
            [52.535770, 33.573364],
            [50.832296, 39.053756]
        ],
        "title":"Курская обл.",
        "center":[51.727387, 36.404295],
        "zoom":8
    },
    {
        "id": 85,
        "mapURL":"mapTAM",
        "bounds": [
            [53.916304, 37.587319],
            [51.535635, 45.534681]
        ],
        "title":"Тамбовская обл.",
        "center":[52.689645, 41.662890],
        "zoom":7.5
    },
    {
        "id": 86,
        "mapURL":"mapTAT",
        "bounds": [
            [56.734828, 45.836817],
            [53.939636, 55.671205]
        ],
        "title":"Татарстан",
        "center":[55.367072, 51.018082],
        "zoom":7.5
    },
    {
        "id": 87,
        "mapURL":"mapTOM",
        "bounds": [
            [61.456520, 70.371695],
            [55.375245, 93.596792]
        ],
        "title":"Томская обл.",
        "center":[58.593342, 82.456656],
        "zoom":7
    },
    {
        "id": 88,
        "mapURL":"mapTUL",
        "bounds": [
            [54.861769, 34.131955],
            [52.923156, 40.762840]
        ],
        "title":"Тульская обл.",
        "center":[53.958951, 37.553742],
        "zoom":9
    },
    {
        "id": 89,
        "mapURL":"mapTVE",
        "bounds": [
            [58.834002, 28.783776],
            [55.728980, 40.589648]
        ],
        "title":"Тверская обл.",
        "center":[57.322382, 35.096484],
        "zoom":7
    },
    {
        "id": 90,
        "mapURL":"mapTYU",
        "bounds": [
            [60.100618, 60.333826],
            [54.958262, 79.510882]
        ],
        "title":"Томская обл.",
        "center":[57.712825, 70.186426],
        "zoom":7
    },
    {
        "id": 91,
        "mapURL":"mapDFO",
        "bounds": [
            [77.20396501293578, 101.49609267711641],
            [38.43810080328941, 195.62695205211645]
        ],
        "title":"Дальний Восток",
        "center":[66.04658044777793, 150.80273330211642],
        "zoom":4
    },
    {
        "id": 1,
        "mapURL":"mapRUS",
        "bounds": [
            [82.091101, 17.782800],
            [31.183870, 167.490653]
         ],
        "title":"Россия",
        "center": [66.51326044311188, 102.16406464576721],
        "zoom": 3
    }
    

]
}